flowillower/__init__.py
flowillower/__init__.pyi
flowillower/_modidx.py
flowillower/core.py
flowillower/help.py
flowillower/nucleus.py
flowillower/flowillower_app_template/__init__.py
flowillower/flowillower_app_template/__init__.pyi
flowillower/flowillower_app_template/src/__init__.py
flowillower/flowillower_app_template/src/__init__.pyi
flowillower/flowillower_app_template/src/streamlit_app.py
flowillower-0.0.3.dist-info/LICENSE
flowillower-0.0.3.dist-info/METADATA
flowillower-0.0.3.dist-info/WHEEL
flowillower-0.0.3.dist-info/entry_points.txt
flowillower-0.0.3.dist-info/top_level.txt
flowillower-0.0.3.dist-info/RECORD
