Metadata-Version: 2.1
Name: flowillower
Version: 0.0.3
Summary: A graceful, distributed, and Git-powered experiment tracking and model explanation tool for AI researchers. See through every forward pass. Flow will over — and flowers will bloom. 一个优雅、分布式的 AI 实验记录与可视化工具，致力于打破模型训练中的“黑盒”迷雾，让每一次 forward 都可见、可溯、可协作 —— 柳暗花明，终见曙光。
Home-page: https://github.com/THU-CVML/flowillower
Author: 叶璨铭 (Ye Canming)
Author-email: ycm24@mails.tsinghua.edu.cn
License: Apache Software License 2.0
Keywords: nbdev jupyter notebook python tensorboard wandb
Classifier: Development Status :: 4 - Beta
Classifier: Intended Audience :: Developers
Classifier: Natural Language :: English
Classifier: Programming Language :: Python :: 3.9
Classifier: Programming Language :: Python :: 3.10
Classifier: Programming Language :: Python :: 3.11
Classifier: Programming Language :: Python :: 3.12
Classifier: License :: OSI Approved :: Apache Software License
Requires-Python: >=3.9
License-File: LICENSE
Requires-Dist: fastcore
Requires-Dist: decorator
Requires-Dist: pydantic
Requires-Dist: mkinit
Requires-Dist: lazy-loader
Requires-Dist: loguru
Requires-Dist: bigmodelvis
Requires-Dist: richuru
Requires-Dist: optuna
Requires-Dist: GitPython
Requires-Dist: tomli-w
Requires-Dist: tomli
Provides-Extra: dev
Requires-Dist: nbdev; extra == "dev"
Requires-Dist: ipykernel; extra == "dev"
